{
    "_id": "4ckf4n0r0uk2mluy",
    "name": "Get Behind Me",
    "type": "ability",
    "system": {
        "description": "You know that you can't explore the world alone, so you've learned to keep your team alive. Any ally within arm's reach of you gains +1 Blood protection thanks to your interventions. Once per situation, you can bellow an order and remove D4 Blood or Mind stress from a nearby ally.",
        "type": "major",
        "minorAbilities": [
            "Compendium.heart.heart.n332cooe3jk5c8lp",
            "Compendium.heart.heart.jc96cbbxeo9d6vxq",
            "Compendium.heart.heart.daccwz3pjc7qw4a2"
        ]
    },
    "_key": "!items!4ckf4n0r0uk2mluy",
    "img": "systems/heart/assets/ability.png",
    "folder": "5P3mjIvR29OhyR6l"
}