{
    "_id": "d5d9vc77q56gvtcj",
    "name": "Thrice-warded",
    "type": "ability",
    "system": {
        "description": "Yo ur bees are marked with auspicious glyphs and you are able to brave the worst of the Heart unscathed. Gain the Cursed domain. Each session, the first time you would take Minor Fortune fallout, avoid the fallout and do not remove stress from Fortune.",
        "type": "minor",
        "minorAbilities": []
    },
    "_key": "!items!d5d9vc77q56gvtcj",
    "img": "systems/heart/assets/ability.png",
    "folder": "5P3mjIvR29OhyR6l"
}